emodjis-0.5.0.dist-info/METADATA
emodjis-0.5.0.dist-info/WHEEL
emodjis/__init__.py
emodjis/__version__.py
emodjis/admin.py
emodjis/components/emoji_grid.py
emodjis/components/login.py
emodjis/components/pagination.py
emodjis/components/search.py
emodjis/filters.py
emodjis/migrations/0001_initial.py
emodjis/migrations/0002_emoji_nsfw_emoji_team.py
emodjis/migrations/0003_emoji_private.py
emodjis/migrations/__init__.py
emodjis/models.py
emodjis/permissions.py
emodjis/routers.py
emodjis/serializers.py
emodjis/templates/base.html
emodjis/templates/bootstrap.html
emodjis/templates/charts_change_list.html
emodjis/templates/client_data.html
emodjis/templates/index.html
emodjis/templates/unicorn/emoji-grid.html
emodjis/templates/unicorn/login.html
emodjis/templates/unicorn/pagination.html
emodjis/templates/unicorn/search.html
emodjis/tests/__init__.py
emodjis/tests/alert.gif
emodjis/tests/blank.png
emodjis/tests/blank.txt
emodjis/urls.py
emodjis/views.py
emodjis/viewsets.py
emodjis-0.5.0.dist-info/RECORD
